{
  "hash": "8e2fef79",
  "configHash": "ba31cfc2",
  "lockfileHash": "c94a8470",
  "browserHash": "162142fa",
  "optimized": {
    "react/jsx-dev-runtime": {
      "src": "../../node_modules/react/jsx-dev-runtime.js",
      "file": "react_jsx-dev-runtime.js",
      "fileHash": "5f0af2e1",
      "needsInterop": true
    },
    "react": {
      "src": "../../node_modules/react/index.js",
      "file": "react.js",
      "fileHash": "5084c00a",
      "needsInterop": true
    },
    "react-dom/client": {
      "src": "../../node_modules/react-dom/client.js",
      "file": "react-dom_client.js",
      "fileHash": "b8c5f32f",
      "needsInterop": true
    }
  },
  "chunks": {
    "chunk-Y455YYDO": {
      "file": "chunk-Y455YYDO.js"
    }
  }
}